icloudpy/__init__.py
icloudpy/base.py
icloudpy/cmdline.py
icloudpy/exceptions.py
icloudpy/utils.py
icloudpy/services/__init__.py
icloudpy/services/account.py
icloudpy/services/calendar.py
icloudpy/services/contacts.py
icloudpy/services/drive.py
icloudpy/services/findmyiphone.py
icloudpy/services/photos.py
icloudpy/services/reminders.py
icloudpy/services/ubiquity.py
icloudpy-0.6.0.dist-info/LICENSE
icloudpy-0.6.0.dist-info/METADATA
icloudpy-0.6.0.dist-info/WHEEL
icloudpy-0.6.0.dist-info/entry_points.txt
icloudpy-0.6.0.dist-info/top_level.txt
icloudpy-0.6.0.dist-info/RECORD
