Metadata-Version: 2.1
Name: icloudpy
Version: 0.6.0
Summary: Python library to interact with iCloud web service
Home-page: https://github.com/mandarons/icloudpy
Author: Mandar Patil
Author-email: mandarons@pm.me
Classifier: Programming Language :: Python :: 3
Classifier: Operating System :: OS Independent
Requires-Python: >=3.8
License-File: LICENSE
Requires-Dist: requests==2.28.1
Requires-Dist: keyring==23.11.0
Requires-Dist: keyrings.alt==4.2.0
Requires-Dist: click==8.1.3
Requires-Dist: six==1.16.0
Requires-Dist: tzlocal==4.2
Requires-Dist: pytz==2022.6
Requires-Dist: certifi==2022.12.7
Requires-Dist: future==0.18.2
